; main.j

; Generated by ClassFileAnalyzer (Can)
; Analyzer and Disassembler for Java class files
; (Jasmin syntax 2, http://jasmin.sourceforge.net)
;
; ClassFileAnalyzer, version 0.7.0 


.bytecode 59.0
.source sample.java
.class main
.super java/lang/Object

.method <init>()V
  .limit stack 1
  .limit locals 1
  .var 0 is this Lmain; from Label0 to Label4
Label0:
  .line 1
  0: aload_0
  1: invokespecial java/lang/Object/<init>()V
Label4:
  4: return
.end method

.method public fy(ILjava/lang/String;)I
  .limit stack 1
  .limit locals 3
  .var 0 is this Lmain; from Label0 to Label1
  .var 1 is num I from Label0 to Label1
  .var 2 is ali Ljava/lang/String; from Label0 to Label1
Label0:
  .line 3
  0: iconst_0
Label1:
  1: ireturn
.end method

.method public static main([Ljava/lang/String;)V
  .limit stack 1
  .limit locals 2
  .var 0 is args [Ljava/lang/String; from Label0 to Label3
  .var 1 is a I from Label3 to Label3
Label0:
  .line 8
  0: bipush 16
  2: istore_1
Label3:
  .line 9
  3: return
.end method


